Workbook

Sheet RACIONAL
A1: MOVE · Maped e Janod · Planilha de apoio e racional do escopo
A2: Base de dados da apresentação "Maped e Janod · Escopo MOVE por frente" · levantamento de 21/10/2026
A4: OBJETIVO | B4: Reunir em um só lugar os números da apresentação, mostrar de onde cada valor veio e deixar claro o que é fato confirmado, o que é projeção e o que ainda depende do cliente.
A5: COMO LER | B5: Texto azul = valor digitado (input, vem de uma fonte). Texto preto = fórmula. Texto verde = fórmula que puxa de outra aba. Fundo amarelo = ponto a confirmar.
A6: ABAS | B6: ESCOPO (todas as linhas faturadas por marca e frente) · RESUMO (totais por frente, calculados do ESCOPO) · VA 2027 (orçamento, BV e faturamento MOVE) · SHOOTING VA (custos e margem) · RESULTADOS (mídia recente) · SEEDING (mailings) · HISTÓRICO (evolução do fee) · MÉXICO (proposta do site) · PENDÊNCIAS.
A8: FONTES
A9: Emissão de NF | B9: Planilha "Emissão NF · Modelo MOVE (a partir de 10-26)", aba 10-26 (emitida). Abas 11-26 e 12-26 repetem os mesmos valores, marcadas como projeção.
A10: NFs de setembro | B10: E-mails de faturamento de 02/10/2026: Maped NFs 3138 (R$ 33.100,00) e 3139 (reembolso R$ 994,53); Janod NFs 3140 (R$ 10.297,50) e 3141 (reembolso R$ 827,36).
A11: DRE e histórico | B11: "Move DRE 2026 v2" e "Move Faturamento Histórico Consolidado 2020 a 2027" (Drive).
A12: Volta às Aulas | B12: Planilha "VA MAPED 2027" (v3 de 08/10/2026), apresentação "Plano de Campanha VA 2027" e e-mail "Investimento dez/jan e mídia por plataforma" de 09/10/2026.
A13: Reuniões | B13: Tactiq: Escopo Maped (24/04/2026), Move I Maped (23/04), Marketplace (27/04), Budget (11/09), weeklies de 25/09, 02/10 e 09/10/2026.
A14: Resultados de mídia | B14: E-mail "[MOVE] Maped · Dados das plataformas de anúncio" (16/10, semana 09 a 16/10) e weekly de 09/10/2026 (Janod).
A15: Site México | B15: Documento "2026-10-20 · MOVE · Propuesta Sitio Maped México" e e-mail "Recrear el sitio web de Janod" (20 e 21/10).
A17: PREMISSAS
A18: 1. Fee | B18: O fee mensal é a soma das linhas com FATURAR = SIM na aba ESCOPO. Linhas inclusas ou bonificadas ficam registradas com valor zero.
A19: 2. Reembolsos | B19: Reembolsos (caixas, fretes, impressos) não fazem parte do fee. São cobrados em NF separada, a custo + 30% de gestão.
A20: 3. Verba de mídia | B20: A verba dos veículos é paga pela Maped direto às plataformas e não passa pelo faturamento da MOVE. Referência de abril/2026: R$ 8.000/mês Maped e R$ 5.000/mês Janod.
A21: 4. BV na Volta às Aulas | B21: A MOVE fatura 20% sobre a verba de mídia e 20% sobre o investimento em influenciadores pagos da campanha (BV), além do seeding.
A22: 5. Mês de referência | B22: O mês da aba de emissão é o mês de emissão da NF; os serviços se referem ao mês anterior.
A24: PONTOS INCERTOS | B24: Ver aba PENDÊNCIAS. Principais: data do shooting VA (22/10 ou 12/11 provisória), linha Shopee com anúncios pausados, Google Maped sem faturamento, aprovação escrita do orçamento VA.

Sheet ESCOPO
A1: Escopo recorrente por marca e frente
A2: Valores mensais de outubro/2026 (iguais em novembro e dezembro, projetados). Fonte principal: emissão de NF aba 10-26.
A4: Marca | B4: Frente | C4: Entrega / detalhamento | D4: Qtd. por mês | E4: Valor mensal | F4: Faturar | G4: Natureza | H4: Responsável MOVE | I4: Fonte / observação
A5: MAPED | B5: Mídia paga e tráfego | C5: Meta: seguidores e engajamento das 14 publicações (5 fotos, 4 gráficos, 5 vídeos) | D5: 14 | E5: 3849 | F5: SIM | G5: Fixo | H5: Gabrielle Duarte | I5: Emissão 10-26
A6: MAPED | B6: Mídia paga e tráfego | C6: Google: branding, concorrentes, YouTube, PMax | E6: 0 | F6: NÃO | G6: Sem valor | H6: Gabrielle Duarte | I6: Emissão 10-26: "sem valor na aba 10/26". Confirmar motivo.
A7: MAPED | B7: Mídia paga e tráfego | C7: TikTok: patrocínio dos 5 vídeos | D7: 5 | E7: 1745 | F7: SIM | G7: Fixo | H7: Gabrielle Duarte | I7: Emissão 10-26
A8: MAPED | B8: Mídia paga e tráfego | C8: Amazon Ads: produtos patrocinados | E8: 1500 | F8: SIM | G8: Fixo | H8: Gabrielle Duarte | I8: Emissão 10-26. Marketplaces entraram em fev/26.
A9: MAPED | B9: Mídia paga e tráfego | C9: Mercado Livre Ads | E9: 1500 | F9: SIM | G9: Fixo | H9: Gabrielle Duarte | I9: Emissão 10-26
A10: MAPED | B10: Mídia paga e tráfego | C10: Shopee Ads | E10: 1500 | F10: SIM | G10: Fixo | H10: Gabrielle Duarte | I10: Anúncios pausados em 01/10 (contrato Lepok). Confirmar com a Maped.
A11: MAPED | B11: SAC 3.0 | C11: Redes: Instagram + stories, Facebook + Messenger, TikTok. Até 1.000 interações, seg a seg, repost 2x ao dia, SLA 24h | D11: 1000 | E11: 6048 | F11: SIM | G11: Fixo | H11: Naiara Capuzzo | I11: Emissão 10-26
A12: MAPED | B12: SAC 3.0 | C12: SAC por e-mail, até 500 mensagens, seg a seg | D12: 500 | E12: 2444 | F12: SIM | G12: Fixo | H12: Naiara Capuzzo | I12: Emissão 10-26
A13: MAPED | B13: SAC 3.0 | C13: Reclamações e envios: planilhas de endereços, controle e acompanhamento | D13: 40 | E13: 2328 | F13: SIM | G13: Fixo | H13: Naiara Capuzzo / Ariene Nogueira | I13: Emissão 10-26
A14: MAPED | B14: SAC 3.0 | C14: RD Station SAC para WhatsApp e automações do bot | E14: 2000 | F14: SIM | G14: Fixo | H14: Naiara Capuzzo | I14: Emissão 10-26
A15: MAPED | B15: SAC 3.0 | C15: Reclame Aqui: atendimento | E15: 0 | F15: NÃO | G15: Bonificado | H15: Naiara Capuzzo | I15: Emissão 10-26
A16: MAPED | B16: Produção de conteúdo | C16: 5 fotos + 4 gráficos | D16: 9 | E16: 3490 | F16: SIM | G16: Fixo | H16: Raquel Da Paz / Laiane Moura | I16: Emissão 10-26
A17: MAPED | B17: Produção de conteúdo | C17: 4 vídeos FR (adaptação do material da Maped França) | D17: 4 | E17: 1596 | F17: SIM | G17: Fixo | H17: Raquel Da Paz | I17: Emissão 10-26
A18: MAPED | B18: Produção de conteúdo | C18: 1 vídeo BR (roteiro e captação MOVE) | D18: 1 | E18: 3000 | F18: SIM | G18: Fixo | H18: Raquel Da Paz | I18: Emissão 10-26
A19: MAPED | B19: Redes sociais e inteligência | C19: 14 Meta · 8 Pinterest · 5 TikTok · 2 YouTube, deck mensal | D19: 29 | E19: 0 | F19: NÃO | G19: Incluso | H19: Ana Beatriz Morgado | I19: Emissão 10-26: incluso no pacote
A20: MAPED | B20: Influenciadores | C20: 7 seedings, MOVE envia (curadoria, mailing, kits, expedição e relatório) | D20: 7 | E20: 2100 | F20: SIM | G20: Fixo | H20: Bia (Influenciadores) | I20: Emissão 10-26. Caixas e fretes no reembolso.
A21: JANOD | B21: Produção de conteúdo | C21: 3 gráficos | D21: 3 | E21: 1139.25 | F21: SIM | G21: Fixo | H21: Carolina Loureiro | I21: Emissão 10-26
A22: JANOD | B22: Produção de conteúdo | C22: 3 fotos | D22: 3 | E22: 1139.25 | F22: SIM | G22: Fixo | H22: Raquel Da Paz | I22: Emissão 10-26
A23: JANOD | B23: Produção de conteúdo | C23: 2 vídeos 9:16 | D23: 2 | E23: 2866.5 | F23: SIM | G23: Fixo | H23: Raquel Da Paz | I23: Emissão 10-26
A24: JANOD | B24: Redes sociais e inteligência | C24: 8 Meta · 8 Pinterest · 2 TikTok · 2 YouTube, relatório mensal | D24: 20 | E24: 0 | F24: NÃO | G24: Incluso | H24: Carolina Loureiro | I24: Emissão 10-26: incluso no pacote
A25: JANOD | B25: Mídia paga e tráfego | C25: Meta: 6 posts + 2 vídeos | D25: 8 | E25: 1250 | F25: SIM | G25: Fixo | H25: Gabrielle Duarte | I25: Emissão 10-26
A26: JANOD | B26: Mídia paga e tráfego | C26: Google: 6 posts + 2 vídeos (branding, concorrentes, YouTube, PMax) | D26: 8 | E26: 1250 | F26: SIM | G26: Fixo | H26: Gabrielle Duarte | I26: Emissão 10-26
A27: JANOD | B27: SAC 3.0 | C27: Facebook e Instagram (feed, direct, stories), FAQ, alinhamento semanal. Checagem 3x ao dia, seg a sex, até 300 interações | D27: 300 | E27: 1752.5 | F27: SIM | G27: Fixo | H27: Naiara Capuzzo | I27: Emissão 10-26
A28: JANOD | B28: Influenciadores | C28: 3 seedings, MOVE envia | D28: 3 | E28: 900 | F28: SIM | G28: Fixo | H28: Bia (Influenciadores) | I28: Emissão 10-26
B30: Fee mensal MAPED | C30: Soma das linhas com Faturar = SIM | E30: =SUMIFS($E$5:$E$28,$A$5:$A$28,"MAPED",$F$5:$F$28,"SIM") -> 33100
B31: Fee mensal JANOD | C31: Soma das linhas com Faturar = SIM | E31: =SUMIFS($E$5:$E$28,$A$5:$A$28,"JANOD",$F$5:$F$28,"SIM") -> 10297.5
B32: Fee mensal do grupo | C32: Maped + Janod | E32: =E30+E31 -> 43397.5
B33: Fee anualizado do grupo | C33: Fee mensal x 12 | E33: =E32*12 -> 520770

Sheet RESUMO
A1: Resumo do fee por frente
A2: Calculado automaticamente a partir da aba ESCOPO (SUMIFS). Participação = valor da frente / fee da marca.
A4: Frente | B4: Maped | C4: % Maped | D4: Janod | E4: % Janod
A5: Produção de conteúdo | B5: =SUMIFS(ESCOPO!$E$5:$E$28,ESCOPO!$A$5:$A$28,"MAPED",ESCOPO!$B$5:$B$28,A5,ESCOPO!$F$5:$F$28,"SIM") -> 8086 | C5: =IF(B$10=0,0,B5/B$10) -> 0.24429003 | D5: =SUMIFS(ESCOPO!$E$5:$E$28,ESCOPO!$A$5:$A$28,"JANOD",ESCOPO!$B$5:$B$28,A5,ESCOPO!$F$5:$F$28,"SIM") -> 5145 | E5: =IF(D$10=0,0,D5/D$10) -> 0.49963583
A6: Redes sociais e inteligência | B6: =SUMIFS(ESCOPO!$E$5:$E$28,ESCOPO!$A$5:$A$28,"MAPED",ESCOPO!$B$5:$B$28,A6,ESCOPO!$F$5:$F$28,"SIM") -> 0 | C6: =IF(B$10=0,0,B6/B$10) -> 0 | D6: =SUMIFS(ESCOPO!$E$5:$E$28,ESCOPO!$A$5:$A$28,"JANOD",ESCOPO!$B$5:$B$28,A6,ESCOPO!$F$5:$F$28,"SIM") -> 0 | E6: =IF(D$10=0,0,D6/D$10) -> 0
A7: Mídia paga e tráfego | B7: =SUMIFS(ESCOPO!$E$5:$E$28,ESCOPO!$A$5:$A$28,"MAPED",ESCOPO!$B$5:$B$28,A7,ESCOPO!$F$5:$F$28,"SIM") -> 10094 | C7: =IF(B$10=0,0,B7/B$10) -> 0.30495468 | D7: =SUMIFS(ESCOPO!$E$5:$E$28,ESCOPO!$A$5:$A$28,"JANOD",ESCOPO!$B$5:$B$28,A7,ESCOPO!$F$5:$F$28,"SIM") -> 2500 | E7: =IF(D$10=0,0,D7/D$10) -> 0.24277737
A8: SAC 3.0 | B8: =SUMIFS(ESCOPO!$E$5:$E$28,ESCOPO!$A$5:$A$28,"MAPED",ESCOPO!$B$5:$B$28,A8,ESCOPO!$F$5:$F$28,"SIM") -> 12820 | C8: =IF(B$10=0,0,B8/B$10) -> 0.38731118 | D8: =SUMIFS(ESCOPO!$E$5:$E$28,ESCOPO!$A$5:$A$28,"JANOD",ESCOPO!$B$5:$B$28,A8,ESCOPO!$F$5:$F$28,"SIM") -> 1752.5 | E8: =IF(D$10=0,0,D8/D$10) -> 0.17018694
A9: Influenciadores | B9: =SUMIFS(ESCOPO!$E$5:$E$28,ESCOPO!$A$5:$A$28,"MAPED",ESCOPO!$B$5:$B$28,A9,ESCOPO!$F$5:$F$28,"SIM") -> 2100 | C9: =IF(B$10=0,0,B9/B$10) -> 0.063444109 | D9: =SUMIFS(ESCOPO!$E$5:$E$28,ESCOPO!$A$5:$A$28,"JANOD",ESCOPO!$B$5:$B$28,A9,ESCOPO!$F$5:$F$28,"SIM") -> 900 | E9: =IF(D$10=0,0,D9/D$10) -> 0.087399854
A10: Total do fee mensal | B10: =SUM(B5:B9) -> 33100 | C10: =SUM(C5:C9) -> 1 | D10: =SUM(D5:D9) -> 10297.5 | E10: =SUM(E5:E9) -> 1
A12: Conferência com a NF de setembro
A13: NF 3138 (Maped) | B13: 33100 | C13: =IF(ABS(B13-B10)<0.01,"OK","DIFERENÇA") -> OK
A14: NF 3140 (Janod) | D14: 10297.5 | E14: =IF(ABS(D14-D10)<0.01,"OK","DIFERENÇA") -> OK
A16: Fee do grupo por mês | B16: =B10+D10 -> 43397.5
A17: Reembolso + 30% (taxa de gestão) | B17: 0.3
A18: Reembolso Maped set/26 (NF 3139) | B18: 994.53
A19: Reembolso Janod set/26 (NF 3141) | B19: 827.36
A20: Faturamento total de setembro (fee + reembolsos) | B20: =B16+B18+B19 -> 45219.39

Sheet VA 2027
A1: Volta às Aulas 2027 · orçamento v3 (08/10/2026)
A2: Campanha de 11/12/2026 a 05/02/2027. Verba de mídia e influenciadores paga pela Maped; MOVE fatura shooting, seeding e BV.
A4: Premissas
A5: BV sobre mídia | B5: 0.2
A6: BV sobre influenciadores pagos | B6: 0.2
A7: Shooting (faturado em outubro) | B7: 18000
A9: Mídia por plataforma (verba do cliente) | B9: Dezembro | C9: Janeiro | D9: Total | E9: Observação
A10: Meta | B10: 12500 | C10: 16000 | D10: =B10+C10 -> 28500
A11: Google | B11: 6000 | C11: 13000 | D11: =B11+C11 -> 19000
A12: TikTok | B12: 6000 | C12: 7000 | D12: =B12+C12 -> 13000
A13: Amazon Ads | B13: 2000 | C13: 7000 | D13: =B13+C13 -> 9000
A14: Pinterest (teste) | B14: 2500 | C14: 3500 | D14: =B14+C14 -> 6000 | E14: Teste, Pinterest pago saiu do fee recorrente
A15: Shopee | B15: 1000 | C15: 3400 | D15: =B15+C15 -> 4400 | E15: Confirmar: anúncios Shopee pausados (Lepok)
A16: Total mídia | B16: =SUM(B10:B15) -> 30000 | C16: =SUM(C10:C15) -> 49900 | D16: =SUM(D10:D15) -> 79900
A18: Outras linhas | B18: Dezembro | C18: Janeiro | D18: Total | E18: Observação
A19: Influenciadores pagos (verba do cliente) | B19: 15000 | C19: 35000 | D19: =B19+C19 -> 50000 | E19: NF historicamente paga pela Maped
A20: Seeding (MOVE) | B20: 6000 | C20: 9000 | D20: =B20+C20 -> 15000 | E20: 20 envios em dez + 30 em jan = 50
A21: BV mídia (MOVE) | B21: =B16*$B$5 -> 6000 | C21: =C16*$B$5 -> 9980 | D21: =B21+C21 -> 15980 | E21: 20% sobre a verba de mídia
A22: BV influenciadores (MOVE) | B22: =B19*$B$6 -> 3000 | C22: =C19*$B$6 -> 7000 | D22: =B22+C22 -> 10000 | E22: 20% sobre influenciadores pagos
A23: Shooting (MOVE, outubro) | D23: =B7 -> 18000 | E23: Ver aba SHOOTING VA
A25: Total da campanha | B25: =B16+B19+B20+B21+B22 -> 60000 | C25: =C16+C19+C20+C21+C22 -> 110880 | D25: =B25+C25+D23 -> 188880 | E25: Deve bater com R$ 188.880 do plano
A26: Faturamento MOVE | B26: =B20+B21+B22 -> 15000 | C26: =C20+C21+C22 -> 25980 | D26: =B26+C26+D23 -> 58980 | E26: Deve bater com R$ 58.980 do plano
A27: Conferência com o plano | D27: =IF(AND(D25=188880,D26=58980),"OK","DIFERENÇA") -> OK
A29: Fase da campanha | B29: Início | C29: Fim | D29: % da verba | E29: Foco
A30: 1. Aquecimento | B30: 11/12/2026 | C30: 23/12/2026 | D30: 0.15 | E30: Lançamento do manifesto, 20 influenciadores de SP com kit em mãos
A31: 2. A Lista | B31: 24/12/2026 | C31: 11/01/2027 | D31: 0.25 | E31: Lista de material, volta com força em 05/01
A32: 3. Pico | B32: 12/01/2027 | C32: 26/01/2027 | D32: 0.4 | E32: Maior verba, segunda e terceira ondas de seeding
A33: 4. Última chamada | B33: 27/01/2027 | C33: 05/02/2027 | D33: 0.2 | E33: Repique até o Carnaval
A34: Total | D34: =SUM(D30:D33) -> 1
A36: Status: aguardando aprovação por escrito de Bianca Dias e Juliana Patudo (orçamento, cronograma e divisão por mês).

Sheet SHOOTING VA
A1: Shooting Volta às Aulas 2027 · custo e margem
A2: Entrega: 8 fotos + 3 vídeos (1 manifesto e 2 de 30s). Studio Dupret, elenco infantil Cintra, sob alvará.
A4: Item | B4: Custo previsto | C4: Observação
A5: Aluguel do estúdio (Studio Dupret) | B5: 1500 | C5: Contrato aprovado por Rodrigo Westphal em 20/10, até 22 pessoas
A6: Videomaker (Will) | B6: 2150 | C6: Willian Beckmann
A7: Fotógrafa (Raphaela Neves) | B7: 800
A8: Elenco infantil (5 crianças) | B8: 3600 | C8: R$ 600 + 20% de agenciamento = R$ 720 por criança
A9: Alvará | B9: 3000 | C9: MOVE é a requerente; Cintra protocola
A10: Alimentação | B10: 1000
A11: Maquiagem | B11: 1000
A12: Figurino | B12: 1000 | C12: Jeans, tênis branco, blusa azul-bebê ou rosa
A13: Custo total previsto | B13: =SUM(B5:B12) -> 14050
A14: Valor faturado à Maped | B14: ='VA 2027'!B7 -> 18000 | C14: Aba VA 2027
A15: Margem MOVE | B15: =B14-B13 -> 3950
A16: Margem % | B16: =IF(B14=0,0,B15/B14) -> 0.21944444
A18: Data | B18: 12/11/2026 | C18: PROVISÓRIA, condicionada ao alvará. E-mails jurídicos citavam 22/10; em 22/10 ficou a diária de vídeos mensais com o Will.

Sheet RESULTADOS
A1: Resultados recentes de mídia
A2: Maped: e-mail de 16/10 (semana 09 a 16/10). Janod: weekly de 09/10/2026. Investimento = verba do cliente.
A4: Marca | B4: Plataforma | C4: Métrica principal | D4: Resultado | E4: Investimento | F4: Vendas | G4: Custo por resultado | H4: ROAS | I4: Observação
A5: MAPED | B5: Meta | C5: Pessoas alcançadas | D5: 88000 | E5: 1078.4 | G5: =IF(OR(D5="",D5=0),"",E5/D5) -> 0.012254545 | H5: =IF(OR(F5="",E5=0),"",F5/E5)
A6: MAPED | B6: Google | C6: Conversões | D6: 1065 | E6: 255.73 | G6: =IF(OR(D6="",D6=0),"",E6/D6) -> 0.24012207 | H6: =IF(OR(F6="",E6=0),"",F6/E6) | I6: 390 cliques
A7: MAPED | B7: TikTok | C7: Visualizações | D7: 61784 | E7: 170.32 | G7: =IF(OR(D7="",D7=0),"",E7/D7) -> 0.0027567008 | H7: =IF(OR(F7="",E7=0),"",F7/E7)
A8: MAPED | B8: Amazon Ads | C8: Vendas atribuídas | E8: 187.54 | F8: 1251.11 | G8: =IF(OR(D8="",D8=0),"",E8/D8) | H8: =IF(OR(F8="",E8=0),"",F8/E8) -> 6.6711635
A9: JANOD | B9: Meta | C9: Alcance | D9: 56000 | E9: 573.85 | G9: =IF(OR(D9="",D9=0),"",E9/D9) -> 0.010247321 | H9: =IF(OR(F9="",E9=0),"",F9/E9) | I9: CTR 2,55%, 530 visitas à landing
A10: JANOD | B10: Google | C10: Conversões | D10: 3118 | E10: 193.06 | G10: =IF(OR(D10="",D10=0),"",E10/D10) -> 0.061917896 | H10: =IF(OR(F10="",E10=0),"",F10/E10) | I10: 127 mil impressões
A11: JANOD | B11: TikTok | C11: Visualizações | D11: 839000 | E11: 210.74 | G11: =IF(OR(D11="",D11=0),"",E11/D11) -> 0.00025117998 | H11: =IF(OR(F11="",E11=0),"",F11/E11) | I11: CTR 3,63%, 845 curtidas

Sheet SEEDING
A1: Mailings de seeding
A2: Maped: 7 por mês. Janod: 3 por mês. Mailings de nov, dez e jan enviados em 21/10.
A4: Marca | B4: Mês | C4: Perfil | D4: Status | E4: Observação
A5: MAPED | B5: Nov/26 | C5: @teacherpaulagabriela | D5: Enviado p/ aprovação 21/10
A6: MAPED | B6: Nov/26 | C6: @jaquesfernandes | D6: Enviado p/ aprovação 21/10
A7: MAPED | B7: Nov/26 | C7: @sofiakalimann | D7: Enviado p/ aprovação 21/10
A8: MAPED | B8: Nov/26 | C8: @mjenckel | D8: Enviado p/ aprovação 21/10
A9: MAPED | B9: Nov/26 | C9: @rebeccaarielloficial | D9: Enviado p/ aprovação 21/10
A10: MAPED | B10: Nov/26 | C10: @gabriellydaf | D10: Enviado p/ aprovação 21/10
A11: MAPED | B11: Nov/26 | C11: @lanas_daily | D11: Enviado p/ aprovação 21/10
A12: MAPED | B12: Dez/26 | C12: @iriscustodiob | D12: Enviado p/ aprovação 21/10
A13: MAPED | B13: Dez/26 | C13: @camilepasquarelli | D13: Enviado p/ aprovação 21/10
A14: MAPED | B14: Dez/26 | C14: @mamaekaren | D14: Enviado p/ aprovação 21/10
A15: MAPED | B15: Dez/26 | C15: @arthuryera | D15: Enviado p/ aprovação 21/10
A16: MAPED | B16: Dez/26 | C16: @maya.dias | D16: Enviado p/ aprovação 21/10
... A30: JANOD | B30: Jan/27 | C30: @rubiatretto | D30: Aprovado 21/10
A32: Contagem
A33: MAPED | B33: Nov/26 | C33: =COUNTIFS($A$5:$A$30,A33,$B$5:$B$30,B33) -> 7
A34: MAPED | B34: Dez/26 | C34: =COUNTIFS($A$5:$A$30,A34,$B$5:$B$30,B34) -> 7
A35: JANOD | B35: Nov/26 | C35: =COUNTIFS($A$5:$A$30,A35,$B$5:$B$30,B35) -> 3
A36: JANOD | B36: Dez/26 | C36: =COUNTIFS($A$5:$A$30,A36,$B$5:$B$30,B36) -> 3
A37: JANOD | B37: Jan/27 | C37: =COUNTIFS($A$5:$A$30,A37,$B$5:$B$30,B37) -> 3

Sheet HISTÓRICO
A1: Evolução do fee mensal
A2: Fonte: abas 10/25 e 11/25 da Emissão Controle, DRE 2026 e Faturamento Histórico Consolidado.
A4: Período | B4: Maped | C4: Janod | D4: O que mudou
A5: Out/2025 | B5: 44121.91 | C5: 10337.49 | D5: Maped com 12 posts, 6 vídeos, Pinterest e Google pagos. Valores incluem reembolso.
A6: Jan/2026 | B6: 35547.82 | D6: Maped: 12 posts e vídeo sem França.
A7: Fev a mai/2026 | B7: 28000 | C7: 8000 | D7: Maped R$ 28 mil (mar a mai). Janod cerca de R$ 8 mil, sem Google. Marketplaces entram em fev/26.
A8: Jun a dez/2026 | B8: =ESCOPO!E30 -> 33100 | C8: =ESCOPO!E31 -> 10297.5 | D8: Escopo por frente (abr/26): 9 posts + 4 vídeos FR + 1 vídeo BR na Maped; Janod com Google de volta e seeding.
A10: Variação jan/26 → atual (Maped) | B10: =IF(B6=0,0,B8/B6-1) -> -0.068859919

Sheet MÉXICO
A1: Proposta: site institucional Maped México
A2: Enviada em 20 e 21/10/2026 a Nathalia Garzón (Maped México), via Bianca Dias e Juliana Patudo. Status: aguardando resposta.
A4: Câmbio de referência (R$ por USD) | B4: 5.43 | E4: Implícito na proposta (R$ 9.500 ≈ USD 1.750). Ajustar se necessário.
A6: Item | B6: Valor (R$) | C6: Recorrência | D6: Valor (USD) | E6: Escopo
A7: Site completo com medição | B7: 9500 | C7: Único | D7: =B7/$B$4 -> 1749.5396 | E7: Arquitetura do janod.com.br em espanhol, catálogo até 200 produtos, onde comprar, blog 3 artigos, GTM, GA4, Consent Mode v2, Search Console, SEO técnico. Hosting do 1º ano incluso.
A8: Manutenção e relatório (opcional) | B8: 1500 | C8: Mensal | D8: =B8/$B$4 -> 276.24309 | E8: Até 10 cadastros ou alterações de produto por mês e relatório mensal
A9: Conteúdo e SEO (opcional) | B9: 2500 | C9: Mensal | D9: =B9/$B$4 -> 460.40516 | E9: 4 artigos por mês
A10: Hosting a partir do 2º ano (sem manutenção) | B10: 600 | C10: Anual | D10: =B10/$B$4 -> 110.49724
A12: Receita do 1º ano com os dois opcionais | B12: =B7+12*(B8+B9) -> 57500 | D12: =B12/$B$4 -> 10589.319 | E12: Site + 12 meses de manutenção e de SEO
A13: Receita do 1º ano só com o site | B13: =B7 -> 9500 | D13: =B13/$B$4 -> 1749.5396

Sheet PENDÊNCIAS
A1: Pendências e pontos a confirmar
A3: # | B3: Marca | C3: Ponto | D3: Detalhe | E3: Quem
A4: 1 | B4: Maped | C4: De acordo da Volta às Aulas | D4: Aprovação por escrito do orçamento v3, cronograma e divisão por mês. | E4: Bianca Dias e Juliana Patudo
A5: 2 | B5: Maped | C5: Alvará e data do shooting | D5: Data provisória 12/11. Assinar contratos da Cintra e do Studio Dupret na Clicksign. | E5: Marina / Jurídico MOVE
A6: 3 | B6: Maped | C6: Linha Shopee na emissão | D6: Anúncios pausados desde 01/10 (Lepok), mas a linha de R$ 1.500 segue na emissão. | E6: Marina com a Maped
A7: 4 | B7: Maped | C7: Google sem faturamento | D7: Linha consta como "não faturar". Confirmar se é bonificação ou suspensão. | E7: Marina
A8: 5 | B8: Ambas | C8: GTM dos sites | D8: Janod sem page_view no GA4; Maped sem medição de cliques em lojas e Fale Conosco. | E8: Cliente / agência do site
A9: 6 | B9: Ambas | C9: Taxa de 30% em contrato | D9: Formalizar a gestão de 30% sobre reembolsos e insumos e como mostrar na NF. | E9: Marina / Jurídico
A10: 7 | B10: Ambas | C10: Escopo 2027 | D10: Renegociação, TikTok Shop e linhas de Janod deixadas para 2027. | E10: Marina
A11: 8 | B11: Maped México | C11: Retorno da proposta do site | D11: Aguardando resposta de Nathalia Garzón. | E11: Bianca / Nathalia
A12: 9 | B12: Janod | C12: Valor da collab Niina Secrets | D12: Valor do contrato não localizado nos e-mails e planilhas. | E12: Bia (Influenciadores)
